{
	"name": {
		"aa": "Bahrain",
		"ab": "Bahrain",
		"ae": "Bahrain",
		"af": "Bahrein",
		"ak": "Baren",
		"am": "ባህሬን",
		"an": "Bahrain",
		"ar": "البحرين",
		"as": "Bahrain",
		"av": "Bahrain",
		"ay": "Bahrain",
		"az": "Bahreyn",
		"ba": "Bahrain",
		"be": "Бахрэйн",
		"bg": "Бахрейн",
		"bh": "Bahrain",
		"bi": "Bahrain",
		"bm": "Bareyini",
		"bn": "বাহরাইন",
		"bo": "བྷཱ་རེན།",
		"br": "Bahrein",
		"bs": "Bahrein",
		"ca": "Bahrain",
		"ce": "Bahrain",
		"ch": "Bahrain",
		"co": "Bahrain",
		"cr": "Bahrain",
		"cs": "Bahrajn",
		"cu": "Bahrain",
		"cv": "Bahrain",
		"cy": "Bahrain",
		"da": "Bahrain",
		"de": "Bahrain",
		"dv": "Bahrain",
		"dz": "བྷ་རེན",
		"ee": "Bahrain nutome",
		"el": "Μπαχρέιν",
		"en": "Bahrain",
		"eo": "Barejno",
		"es": "Baréin",
		"et": "Bahrein",
		"eu": "Bahrain",
		"fa": "بحرين",
		"ff": "Bahreyn",
		"fi": "Bahrain",
		"fj": "Bahrain",
		"fo": "Bahrain",
		"fr": "Bahreïn",
		"fy": "De Barein",
		"ga": "Bairéin",
		"gd": "Bachrain",
		"gl": "Bahrein",
		"gn": "Bahrain",
		"gu": "બેહરીન",
		"gv": "Bahrain",
		"ha": "Baharan",
		"he": "בחריין",
		"hi": "बाहरेन",
		"ho": "Bahrain",
		"hr": "Bahrein",
		"ht": "Bahrain",
		"hu": "Bahrein",
		"hy": "Բահրեյն",
		"hz": "Bahrain",
		"ia": "Bahrain",
		"id": "Bahrain",
		"ie": "Bahrain",
		"ig": "Bahrain",
		"ii": "Bahrain",
		"ik": "Bahrain",
		"io": "Bahrain",
		"is": "Barein",
		"it": "Bahrain",
		"iu": "Bahrain",
		"ja": "バーレーン",
		"jv": "Bahrain",
		"ka": "ბაჰრეინი",
		"kg": "Bahrain",
		"ki": "Bahareni",
		"kj": "Bahrain",
		"kk": "Бахрейн",
		"kl": "Bahrain",
		"km": "បារ៉ែន",
		"kn": "ಬಹರೈನ್",
		"ko": "바레인",
		"kr": "Bahrain",
		"ks": "بحریٖن",
		"ku": "Behreyn",
		"kv": "Bahrain",
		"kw": "Baghreyn",
		"ky": "Bahrain",
		"la": "Baharina",
		"lb": "Bahrain",
		"lg": "Baareeni",
		"li": "Bahrein",
		"ln": "Bahrɛnɛ",
		"lo": "ບາເລນ",
		"lt": "Bahreinas",
		"lu": "Bahrain",
		"lv": "Bahreina",
		"mg": "Bahrain",
		"mh": "Bahrain",
		"mi": "Bahrain",
		"mk": "Бахреин",
		"ml": "ബഹ്റൈൻ",
		"mn": "Бахрейн",
		"mr": "बहारीन",
		"ms": "Bahrain",
		"mt": "Baħrajn",
		"my": "ဘာရိန်း",
		"na": "Bahrain",
		"nb": "Bahrain",
		"nd": "Bahrain",
		"ne": "बाह्रेन",
		"ng": "Bahrain",
		"nl": "Bahrein",
		"nn": "Bahrain",
		"no": "Bahrain",
		"nr": "Bahrain",
		"nv": "Bahrain",
		"ny": "Bahrain",
		"oc": "Bahrain",
		"oj": "Bahrain",
		"om": "Bahrain",
		"or": "ବାହାରିନ୍",
		"os": "Bahrain",
		"pa": "Bahrain",
		"pi": "Bahrain",
		"pl": "Bahrajn",
		"ps": "Bahrain",
		"pt": "Bahrein",
		"qu": "Bahrain",
		"rm": "Bahrain",
		"rn": "Bahareyini",
		"ro": "Bahrein",
		"ru": "Бахрейн",
		"rw": "Bahrain",
		"sa": "Bahrain",
		"sc": "Bahrain",
		"sd": "Bahrain",
		"se": "Bahrain",
		"sg": "Bahrâina",
		"si": "බහරේන්",
		"sk": "Bahrajn",
		"sl": "Bahrajn",
		"sm": "Bahrain",
		"sn": "Bahareni",
		"so": "Baxreyn",
		"sq": "Bahrein",
		"sr": "Бахреин",
		"ss": "Bahrain",
		"st": "Bahrain",
		"su": "Bahrain",
		"sv": "Bahrain",
		"sw": "Bahareni",
		"ta": "பஹ்ரைன்",
		"te": "బహరేన్",
		"tg": "Bahrain",
		"th": "ประเทศบาห์เรน",
		"ti": "ባህሬን",
		"tk": "Bahrain",
		"tl": "Bahrain",
		"tn": "Bahrain",
		"to": "Paleini",
		"tr": "Bahreyn",
		"ts": "Bahrain",
		"tt": "Bahrain",
		"tw": "Bahrain",
		"ty": "Bahrain",
		"ug": "Bahrain",
		"uk": "Бахрейн",
		"ur": "بحرین",
		"uz": "Baxreyn",
		"ve": "Bahrain",
		"vi": "Bahrain",
		"vo": "Bahruäns",
		"wa": "Bahrain",
		"wo": "Bahrain",
		"xh": "Bahrain",
		"yi": "Bahrain",
		"yo": "Orílẹ́ède Báránì",
		"za": "Bahrain",
		"zh": "巴林",
		"zu": "i-Bahrain"
	},
	"alt": []
}
