{
	"name": {
		"aa": "Greenland",
		"ab": "Greenland",
		"ae": "Greenland",
		"af": "Groenland",
		"ak": "Greenman",
		"am": "ግሪንላንድ",
		"an": "Gronlandia",
		"ar": "غرينلاند",
		"as": "Greenland",
		"av": "Greenland",
		"ay": "Greenland",
		"az": "Qrinland",
		"ba": "Greenland",
		"be": "Грэнландыя",
		"bg": "Гренландия",
		"bh": "Greenland",
		"bi": "Greenland",
		"bm": "Gɔrɔhenelandi",
		"bn": "গ্রিনল্যান্ড",
		"bo": "གེ་རེན་ལ",
		"br": "Greunland",
		"bs": "Grenland",
		"ca": "Grenlàndia",
		"ce": "Greenland",
		"ch": "Greenland",
		"co": "Greenland",
		"cr": "Greenland",
		"cs": "Grónsko",
		"cu": "Greenland",
		"cv": "Гренланди",
		"cy": "Yr Ynys Las",
		"da": "Grønland",
		"de": "Grönland",
		"dv": "ގުރީންލޭންޑު",
		"dz": "གིརཱིན་ལནཌ྄",
		"ee": "Grinland nutome",
		"el": "Γροιλανδία",
		"en": "Greenland",
		"eo": "Gronlando",
		"es": "Groenlandia",
		"et": "Gröönimaa",
		"eu": "Groenlandia",
		"fa": "گرینلند",
		"ff": "Gorwendland",
		"fi": "Grönlanti",
		"fj": "Greenland",
		"fo": "Grønland",
		"fr": "Groenland",
		"fy": "Grienlân",
		"ga": "An Ghraonlainn",
		"gd": "A' Ghraonlainn",
		"gl": "Grenlandia",
		"gn": "Kyoẽlándia",
		"gu": "ગ્રીનલેન્ડ",
		"gv": "Greenlynn",
		"ha": "Grinlan",
		"he": "גרינלנד",
		"hi": "ग्रीनलैण्ड",
		"ho": "Greenland",
		"hr": "Grenland",
		"ht": "Greenland",
		"hu": "Grönland",
		"hy": "Գրենլանդիա",
		"hz": "Greenland",
		"ia": "Groenlandia",
		"id": "Greenland",
		"ie": "Grenland",
		"ig": "Greenland",
		"ii": "Greenland",
		"ik": "Greenland",
		"io": "Grenlando",
		"is": "Grænland",
		"it": "Groenlandia",
		"iu": "ᐊᑯᑭᑦᑐᑦ",
		"ja": "グリーンランド",
		"jv": "Greenland",
		"ka": "გრენლანდია",
		"kg": "Greenland",
		"ki": "Grinlandi",
		"kj": "Greenland",
		"kk": "Гренландия",
		"kl": "Kalaallit Nunaat",
		"km": "ហ្គ្រោអង់ឡង់",
		"kn": "ಗ್ರೀನ್‍ಲ್ಯಾಂಡ್",
		"ko": "그린란드",
		"kr": "Greenland",
		"ks": "گریٖنلینٛڑ",
		"ku": "Grînlenda",
		"kv": "Гренландия",
		"kw": "Greunlond",
		"ky": "Greenland",
		"la": "Groenlandia",
		"lb": "Grönland",
		"lg": "Gurenelandi",
		"li": "Greunland",
		"ln": "Gowelande",
		"lo": "ກຣີນແລນ",
		"lt": "Grenlandija",
		"lu": "Greenland",
		"lv": "Grenlande",
		"mg": "Groenland",
		"mh": "Greenland",
		"mi": "Greenland",
		"mk": "Гренланд",
		"ml": "ഗ്രീന്‍ലാന്‍ഡ്",
		"mn": "Гренланд",
		"mr": "ग्रीनलँड",
		"ms": "Greenland",
		"mt": "Grinlandja",
		"my": "ဂရင်းလန်း",
		"na": "Greenland",
		"nb": "Greenland",
		"nd": "Greenland",
		"ne": "ग्रिनल्याण्ड",
		"ng": "Greenland",
		"nl": "Groenland",
		"nn": "Grønland",
		"no": "Grønland",
		"nr": "Greenland",
		"nv": "Haʼaʼaahjí Hakʼaz Dineʼé Bikéyah",
		"ny": "Greenland",
		"oc": "Groenlàndia",
		"oj": "Greenland",
		"om": "Greenland",
		"or": "ଗ୍ରୀନଲ୍ୟାଣ୍ଡ",
		"os": "Гренланди",
		"pa": "ਗਰੀਨਲੈਂਡ",
		"pi": "Greenland",
		"pl": "Grenlandia",
		"ps": "Greenland",
		"pt": "Gronelândia",
		"qu": "Kalalit Nunat",
		"rm": "Grönlanda",
		"rn": "Gurunilandi",
		"ro": "Groenlanda",
		"ru": "Гренландия",
		"rw": "Goronulande",
		"sa": "Greenland",
		"sc": "Greenland",
		"sd": "Greenland",
		"se": "Kalaallit Nunaat",
		"sg": "Gorolânde",
		"si": "ග්‍රීන්ලන්තය",
		"sk": "Grónsko",
		"sl": "Grenlandija",
		"sm": "Greenland",
		"sn": "Greenland",
		"so": "Greenland",
		"sq": "Grenlanda",
		"sr": "Гренланд",
		"ss": "Greenland",
		"st": "Greenland",
		"su": "Lemah Héjo",
		"sv": "Grönland",
		"sw": "Greenland",
		"ta": "கிறீன்லாந்து",
		"te": "గ్రీన్‌లాండ్",
		"tg": "Гренландия",
		"th": "กรีนแลนด์",
		"ti": "ግሪንላንድ",
		"tk": "Greenland",
		"tl": "Lupanlunti",
		"tn": "Greenland",
		"to": "Kulinileni",
		"tr": "Grönland",
		"ts": "Greenland",
		"tt": "Гренландия",
		"tw": "Greenland",
		"ty": "Greenland",
		"ug": "Grénlandiye",
		"uk": "Ґренландія",
		"ur": "گرین لینڈ",
		"uz": "Greenland",
		"ve": "Greenland",
		"vi": "Greenland",
		"vo": "Gröneän",
		"wa": "Greenland",
		"wo": "Groenlaand",
		"xh": "Greenland",
		"yi": "גרינלאנד",
		"yo": "Orílẹ́ède Gerelandi",
		"za": "Greenland",
		"zh": "格陵兰",
		"zu": "i-Greenland"
	},
	"alt": ["Groenlando", "Groenlândia"]
}
