{
	"name": {
		"aa": "New Zealand",
		"ab": "New Zealand",
		"ae": "New Zealand",
		"af": "Nieu-Seeland",
		"ak": "Ziland Foforo",
		"am": "ኒው ዚላንድ",
		"an": "Nueva Zelanda",
		"ar": "نيوزيلندا",
		"as": "New Zealand",
		"av": "New Zealand",
		"ay": "New Zealand",
		"az": "Yeni Zelandiya",
		"ba": "Яңы Зеландия",
		"be": "Новая Зеландыя",
		"bg": "Нова Зеландия",
		"bh": "New Zealand",
		"bi": "Niu Zilan",
		"bm": "Zelandi Koura",
		"bn": "নিউ জিলণ্ড",
		"bo": "ནིའུ་ཛི་ལན྄ཌ།",
		"br": "Zeland Nevez",
		"bs": "Novi Zeland",
		"ca": "Nova Zelanda",
		"ce": "New Zealand",
		"ch": "New Zealand",
		"co": "New Zealand",
		"cr": "New Zealand",
		"cs": "Nový Zéland",
		"cu": "New Zealand",
		"cv": "Ҫӗнӗ Зеланди",
		"cy": "Seland Newydd",
		"da": "New Zealand",
		"de": "Neuseeland",
		"dv": "ނިއުޒިލޭންޑު",
		"dz": "ནིའུ་ཛི་ལེནཌ",
		"ee": "New Zealand nutome",
		"el": "Νέα Ζηλανδία",
		"en": "New Zealand",
		"eo": "Nov-Zelando",
		"es": "Nueva Zelanda",
		"et": "Uus-Meremaa",
		"eu": "Zeelanda Berria",
		"fa": "نیوزیلند",
		"ff": "Nuwel Selannda",
		"fi": "Uusi-Seelanti",
		"fj": "New Zealand",
		"fo": "Ný Sæland",
		"fr": "Nouvelle-Zélande",
		"fy": "Nij-Seelân",
		"ga": "An Nua-Shéalainn",
		"gd": "Sealainn Nuadh",
		"gl": "Nova Celandia",
		"gn": "New Zealand",
		"gu": "ન્યુઝીલેન્ડ",
		"gv": "Yn Teelynn Noa",
		"ha": "Nuzilan",
		"he": "ניו זילנד",
		"hi": "न्यूज़ीलैंड",
		"ho": "New Zealand",
		"hr": "Novi Zeland",
		"ht": "Nouvèl Zelann",
		"hu": "Új-Zéland",
		"hy": "Նոր Զելանդիա",
		"hz": "New Zealand",
		"ia": "Nove Zelanda",
		"id": "Selandia Baru",
		"ie": "Nov-Zeland",
		"ig": "New Zealand",
		"ii": "New Zealand",
		"ik": "New Zealand",
		"io": "Nova-Zelando",
		"is": "Nýja-Sjáland",
		"it": "Nuova Zelanda",
		"iu": "New Zealand",
		"ja": "ニュージーランド",
		"jv": "Sélandia Anyar",
		"ka": "ახალი ზელანდია",
		"kg": "New Zealand",
		"ki": "Nyuzilandi",
		"kj": "New Zealand",
		"kk": "Жаңа Зеландия",
		"kl": "Nutaaq Zeelandi",
		"km": "នូវែលហ្សេឡង់",
		"kn": "ನ್ಯೂಜಿಲೆಂಡ್",
		"ko": "뉴질랜드",
		"kr": "New Zealand",
		"ks": "نیوٗزِلینٛڑ",
		"ku": "Zêlanda Nû",
		"kv": "Выль Зеландия",
		"kw": "Mordir Nowydh",
		"ky": "New Zealand",
		"la": "Nova Zelandia",
		"lb": "Neiséiland",
		"lg": "Niyuziirandi",
		"li": "Nui-Zieland",
		"ln": "Zelandɛ ya sika",
		"lo": "ນິວຊີແລນ",
		"lt": "Naujoji Zelandija",
		"lu": "New Zealand",
		"lv": "Jaunzēlande",
		"mg": "Nouvelle-Zélande",
		"mh": "New Zealand",
		"mi": "Aotearoa",
		"mk": "Нов Зеланд",
		"ml": "ന്യൂസിലാൻറ്",
		"mn": "Шинэ Зеланд",
		"mr": "न्यूझीलंड",
		"ms": "New Zealand",
		"mt": "New Zealand",
		"my": "နယူးဇီလန်",
		"na": "Niu Djiran",
		"nb": "New Zealand",
		"nd": "New Zealand",
		"ne": "न्युजिल्यान्ड",
		"ng": "New Zealand",
		"nl": "Nieuw-Zeeland",
		"nn": "New Zealand",
		"no": "New Zealand",
		"nr": "New Zealand",
		"nv": "New Zealand",
		"ny": "New Zealand",
		"oc": "Nòva Zelanda",
		"oj": "New Zealand",
		"om": "New Zealand",
		"or": "ନ୍ୟୁଜିଲାଣ୍ଡ",
		"os": "Ног Зеланди",
		"pa": "ਨਿਊਜ਼ੀਲੈਂਡ",
		"pi": "New Zealand",
		"pl": "Nowa Zelandia",
		"ps": "نیوزیلنډ",
		"pt": "Nova Zelândia",
		"qu": "Musuq Silanda",
		"rm": "Nova Zelanda",
		"rn": "Nuvelizelandi",
		"ro": "Noua Zeelandă",
		"ru": "Новая Зеландия",
		"rw": "Nuveli Zelande",
		"sa": "न्यू-जीलैंड",
		"sc": "New Zealand",
		"sd": "New Zealand",
		"se": "Aotearoa",
		"sg": "Finî Zelânde",
		"si": "නවසීලන්තය",
		"sk": "Nový Zéland",
		"sl": "Nova Zelandija",
		"sm": "Niu Sila",
		"sn": "New Zealand",
		"so": "Neyuusilaand",
		"sq": "Zelanda e Re",
		"sr": "Нови Зеланд",
		"ss": "New Zealand",
		"st": "New Zealand",
		"su": "Selandia Anyar",
		"sv": "Nya Zeeland",
		"sw": "Nyuzilandi",
		"ta": "நியூசிலாந்து",
		"te": "న్యుజిలేండ్",
		"tg": "Зеландияи Нав",
		"th": "ประเทศนิวซีแลนด์",
		"ti": "ኒው ዚላንድ",
		"tk": "Täze Zelandiýa",
		"tl": "New Zealand",
		"tn": "New Zealand",
		"to": "Nuʻusila",
		"tr": "Yeni Zelanda",
		"ts": "New Zealand",
		"tt": "Яңа Зеландия",
		"tw": "New Zealand",
		"ty": "Aotearoa",
		"ug": "يېڭى زېلاندىيە",
		"uk": "Нова Зеландія",
		"ur": "نیوزی ینڈ",
		"uz": "Yangi Zelandiya",
		"ve": "New Zealand",
		"vi": "Niu Di-lân",
		"vo": "Nula-Seleäns",
		"wa": "Nouve Zelande",
		"wo": "Seland-Gu-Bees",
		"xh": "New Zealand",
		"yi": "ניו זילאנד",
		"yo": "Orílẹ́ède ṣilandi Titun",
		"za": "Saen Saelanz",
		"zh": "紐西蘭/新西兰",
		"zu": "i-New Zealand"
	},
	"alt": ["아오테아로아"]
}
