{
	"name": {
		"aa": "Svalbard e Jan Mayen",
		"ab": "Свалбард и Ян Майен",
		"ae": "Svalbard e Jan Mayen",
		"af": "Svalbard en Jan Mayen",
		"ak": "Svalbard ne Jan Mayen",
		"am": "ስቫልባርድ እና ጃን ማይን",
		"an": "Svalbard y Jan Mayen",
		"ar": "سفالبارد وجزيرة جان مايكل",
		"as": "স্বালবার্ড আৰু জান ময়েন",
		"av": "Свалбард и Ян Майен",
		"ay": "Svalbard and Jan Mayen",
		"az": "Svalbard və Jan Mayen",
		"ba": "Свалбард һәм Ян Майен",
		"be": "Свалбарда і Ян Майен",
		"bg": "Свалбард и Ян Майен",
		"bh": "Svalbard aur Jan Mayen",
		"bi": "Svalbard and Jan Mayen",
		"bm": "Svalbard ak Jan Mayen",
		"bn": "স্বালবার্ড এবং জান মায়েন",
		"bo": "སྭབ་དར་དང་ཡན་མ་ཨེན",
		"br": "Svalbard ha Jan Mayen",
		"bs": "Svalbard i Jan Mayen",
		"ca": "Svalbard i Jan Mayen",
		"ce": "Свалбард и Ян Майен",
		"ch": "Svalbard and Jan Mayen",
		"co": "Svalbard è Jan Mayen",
		"cr": "Svalbard and Jan Mayen",
		"cs": "Svalbard a Jan Mayen",
		"cu": "Свалбард и Ян Майен",
		"cv": "Свалбард и Ян Майен",
		"cy": "Svalbard a Jan Mayen",
		"da": "Svalbard og Jan Mayen",
		"de": "Svalbard und Jan Mayen",
		"dv": "ސްވާބަދު އިނަގައިން",
		"dz": "སྲུལ་བཱར་དང་ཡན་མ་ཨེན",
		"ee": "Svalbard na Jan Mayen",
		"el": "Σβάλμπαρντ και Γιάν Μάγιεν",
		"en": "Svalbard and Jan Mayen",
		"eo": "Svalbardo kaj Jan Mayen",
		"es": "Svalbard y Jan Mayen",
		"et": "Svalbard ja Jan Mayen",
		"eu": "Svalbard eta Jan Mayen",
		"fa": "سوالبارد و جزیره جان ماین",
		"ff": "Svalbard e Jan Mayen",
		"fi": "Svalbard ja Jan Mayen",
		"fj": "Svalbard kei Jan Mayen",
		"fo": "Svalbard og Jan Mayen",
		"fr": "Svalbard et Jan Mayen",
		"fy": "Svalbard en Jan Mayen",
		"ga": "Svalbard agus Jan Mayen",
		"gd": "Svalbard agus Jan Mayen",
		"gl": "Svalbard e Jan Mayen",
		"gn": "Svalbard ha Jan Mayen",
		"gu": "સ્વાલ્બાર્ડ અને જાન માયેન",
		"gv": "Svalbard as Jan Mayen",
		"ha": "Svalbard da Jan Mayen",
		"he": "סבאלבארד וגן מיין",
		"hi": "स्वालबार्ड और जान मेयन",
		"ho": "Svalbard and Jan Mayen",
		"hr": "Svalbard i Jan Mayen",
		"ht": "Svalbard ak Jan Mayen",
		"hu": "Svalbard és Jan Mayen",
		"hy": "Սվալբարդ և Յան Մայեն",
		"hz": "Svalbard and Jan Mayen",
		"ia": "Svalbard e Jan Mayen",
		"id": "Svalbard dan Jan Mayen",
		"ie": "Svalbard e Jan Mayen",
		"ig": "Svalbard na Jan Mayen",
		"ii": "Svalbard and Jan Mayen",
		"ik": "Svalbard e Jan Mayen",
		"io": "Svalbard e Jan Mayen",
		"is": "Svalbard og Jan Mayen",
		"it": "Svalbard e Jan Mayen",
		"iu": "Svalbard and Jan Mayen",
		"ja": "スヴァールバルとヤン・マイエン",
		"jv": "Svalbard lan Jan Mayen",
		"ka": "სვალბარდი და იან მეიენი",
		"kg": "Svalbard e Jan Mayen",
		"ki": "Svalbard na Jan Mayen",
		"kj": "Svalbard and Jan Mayen",
		"kk": "Свалбард және Ян Майен",
		"kl": "Svalbard aamma Jan Mayen",
		"km": "ស្វាល់បារ៉ដ និង ចាន់ម៉ាយអេន",
		"kn": "ಸ್ವಾಲ್ಬಾರ್ಡ್ ಮತ್ತು ಜಾನ್ ಮಯೆನ್",
		"ko": "스발바르와 얀 마옌",
		"kr": "Svalbard and Jan Mayen",
		"ks": "سوالبارد ۽ جان مائين",
		"ku": "Svalbard û Jan Mayen",
		"kv": "Свалбард и Ян Майен",
		"kw": "Svalbard ha Jan Mayen",
		"ky": "Свалбард жана Ян Майен",
		"la": "Svalbard et Jan Mayen",
		"lb": "Svalbard a Jan Mayen",
		"lg": "Svalbard ne Jan Mayen",
		"li": "Svalbard en Jan Mayen",
		"ln": "Svalbard na Jan Mayen",
		"lo": "ສະວາລບາດ ແລະ ຈານ ແມຍເນ",
		"lt": "Svalbardas ir Jan Mayen",
		"lu": "Svalbard e Jan Mayen",
		"lv": "Svalbarda un Jan Mayen",
		"mg": "Svalbard sy Jan Mayen",
		"mh": "Svalbard and Jan Mayen",
		"mi": "Svalbard me Jan Mayen",
		"mk": "Свалбард и Јан Мајен",
		"ml": "സ്വാല്ബാർഡ് ആൻഡ് ജാൻ മെയൻ",
		"mn": "Свалбард, Ян Майен",
		"mr": "स्वालबार्ड आणि जान मयेन",
		"ms": "Svalbard dan Jan Mayen",
		"mt": "Svalbard u Jan Mayen",
		"my": "Svalbard dan Jan Mayen",
		"na": "Svalbard e Jan Mayen",
		"nb": "Svalbard og Jan Mayen",
		"nd": "Svalbard and Jan Mayen",
		"ne": "स्वाल्बार्ड र जान मयेन",
		"ng": "Svalbard and Jan Mayen",
		"nl": "Svalbard en Jan Mayen",
		"nn": "Svalbard og Jan Mayen",
		"no": "Svalbard og Jan Mayen",
		"nr": "Svalbard e Jan Mayen",
		"nv": "Svalbard e Jan Mayen",
		"ny": "Svalbard ndi Jan Mayen",
		"oc": "Svalbard e Jan Mayen",
		"oj": "Svalbard and Jan Mayen",
		"om": "Svalbard fi Jan Mayen",
		"or": "ସ୍ୱାଲବାର୍ଡ ଓ ଜାନ ମୟେନ",
		"os": "Свалбард и Ян Майен",
		"pa": "ਸਵਾਲਬਾਰਡ ਅਤੇ ਜਾਨ ਮਯੈਨ",
		"pi": "Svalbard and Jan Mayen",
		"pl": "Svalbard i Jan Mayen",
		"ps": "سوالبارد او جان ماین",
		"pt": "Svalbard e Jan Mayen",
		"qu": "Svalbard ni Jan Mayen",
		"rm": "Svalbard e Jan Mayen",
		"rn": "Svalbard na Jan Mayen",
		"ro": "Svalbard și Jan Mayen",
		"ru": "Шпицберген и Ян Майен",
		"rw": "Svalbard na Jan Mayen",
		"sa": "स्वाल्बार्ड आणि जान मयेन",
		"sc": "Svalbard e Jan Mayen",
		"sd": "Svalbard and Jan Mayen",
		"se": "Svalbard ja Jan Mayen",
		"sg": "Svalbard na Jan Mayen",
		"si": "ස්වාල්බර්ඩ් සහ ජන මයෙන්",
		"sk": "Svalbard a Jan Mayen",
		"sl": "Svalbard in Jan Mayen",
		"sm": "Svalbard ma Jan Mayen",
		"sn": "Svalbard ne Jan Mayen",
		"so": "Svalbard iyo Jan Mayen",
		"sq": "Svalbard dhe Jan Mayen",
		"sr": "Свалбард и Јан Мајен",
		"ss": "Svalbard na Jan Mayen",
		"st": "Svalbard le Jan Mayen",
		"su": "Svalbard jeung Jan Mayen",
		"sv": "Svalbard och Jan Mayen",
		"sw": "Svalbard na Jan Mayen",
		"ta": "ஸ்வால்பார்ட் மற்றும் ஜான் மயேன்",
		"te": "స్వాల్బార్డ్ మరియు జాన్ మయెన్",
		"tg": "Свалбард ва Ян Майен",
		"th": "สฟาลบาร์ดและยานมาเยน",
		"ti": "ስቫልባርድ እና ጃን ማይን",
		"tk": "Svalbard we Jan Mayen",
		"tl": "Svalbard at Jan Mayen",
		"tn": "Svalbard le Jan Mayen",
		"to": "Svalbard mo Jan Mayen",
		"tr": "Svalbard ve Jan Mayen",
		"ts": "Svalbard na Jan Mayen",
		"tt": "Свалбард һәм Ян Майен",
		"tw": "Svalbard na Jan Mayen",
		"ty": "Svalbard e Jan Mayen",
		"ug": "Svalbard we Jan Mayen",
		"uk": "Шпіцберген і Ян-Маєн",
		"ur": "سوالبارڈ اور جان ماین",
		"uz": "Svalbard va Jan Mayen",
		"ve": "Svalbard na Jan Mayen",
		"vi": "Svalbard và Jan Mayen",
		"vo": "Svalbard e Jan Mayen",
		"wa": "Svalbard et Jan Mayen",
		"wo": "Svalbard ak Jan Mayen",
		"xh": "Svalbard no Jan Mayen",
		"yi": "סוואַלבאַרד און יאַן מייַען",
		"yo": "Svalbard ati Jan Mayen",
		"za": "Svalbard and Jan Mayen",
		"zh": "斯瓦尔巴和扬麦恩",
		"zu": "Svalbard no Jan Mayen"
	},
	"alt": ["Svalbard og Jan Mayen", "Svalbard", "Jan Mayen"]
}
